_hgraph/_hgraph.cpython-312-x86_64-linux-gnu.so
hg_cpp/__init__.py
hg_cpp/_builder_factories.py
hg_cpp-0.0.5.dist-info/RECORD
hg_cpp-0.0.5.dist-info/METADATA
hg_cpp-0.0.5.dist-info/WHEEL
hg_cpp-0.0.5.dist-info/licenses/LICENSE
