Metadata-Version: 2.1
Name: hg_cpp
Version: 0.0.5
Summary: A C++ performance runtime engine for HGraph
Keywords: reactive,graph,fpg,forward propogating graph,time series,functional reactive programming
Author-Email: Howard Henson <howard@henson.me.uk>
License: MIT License
Classifier: Development Status :: 3 - Alpha
Classifier: Programming Language :: Python
Classifier: Programming Language :: Python :: 3.12
Classifier: Programming Language :: Python :: Implementation :: CPython
Classifier: Programming Language :: C++
Project-URL: Homepage, https://github.com/hhenson/hg_cpp
Project-URL: Repository, https://github.com/hhenson/hg_cpp.git
Requires-Python: >=3.12
Requires-Dist: hgraph>=0.3.37
